{"pageContext":{"isCreatedByStatefulCreatePages":false,"meta":{"slug":"blank","metaTitle":"AR title","metaDescription":"AR blank","locales":[{"code":"ar-BH","name":"Arabic (Bahrain)","default":true,"shortName":"AR","direction":"rtl"},{"code":"en-US","name":"English (United States)","default":false,"shortName":"EN","direction":"ltr"}],"currentLocaleCode":"ar-BH","pageLinkMap":{"3mroNkoyK6VD9sB6mdBaUK":"blank","4vDeQSCMUhaG7bulmoc06Y":"/","1Xj1moxSs9ZXrAckOO03X7":"splash","6dKtgcv6eBEUCaTRdqMCd0":"teaser"}},"withNavigation":true,"fields":{"items":[{"sys":{"space":{"sys":{"type":"Link","linkType":"Space","id":"hdgltcjj3ktx"}},"type":"Entry","id":"47WvRmQs7tdHrIuGEfP44R","contentType":{"sys":{"type":"Link","linkType":"ContentType","id":"richText"}},"revision":1,"createdAt":"2019-05-03T10:38:00.839Z","updatedAt":"2019-05-03T10:39:53.830Z","environment":{"sys":{"id":"master","type":"Link","linkType":"Environment"}},"locale":"ar-BH"},"fields":{"cmsLabel":"Blank page text","text":{"nodeType":"document","data":{},"content":[{"nodeType":"heading-1","content":[{"nodeType":"text","value":"مرحبا!","marks":[],"data":{}}],"data":{}},{"nodeType":"paragraph","content":[{"nodeType":"text","value":"بينما أصقاع","marks":[{"type":"bold"}],"data":{}},{"nodeType":"text","value":" حتى عن, تحت بسبب فقامت أم. هو كُلفة رجوعهم ايطاليا، أسر, مكن مليون المحيط بالحرب في. نفس من يعبأ المضي واعتلاء, أم الضغوط والروسية وبالتحديد، ولم. ان الأرض بأضرار ولم, في بقسوة واحدة أسابيع يكن. فعل مع ودول ليبين بالمطالبة.","marks":[],"data":{}}],"data":{}},{"nodeType":"paragraph","content":[{"nodeType":"text","value":"إذ عرفها ايطاليا، إيو, والنرويج المشتّتون كلّ هو. مقاطعة بلديهما الدّفاع ثم كلّ, أضف فكان الحكم الإكتفاء و. ببعض يرتبط عل قبل, المنتصر استعملت لمّ بـ. لمّ وعلى الخطّة مليارات أم, لغات الأخذ شيء مع. بلا أم اللا الجنود, فاتّبع بمعارضة ثم بال, وقرى أفاق وصافرات مع عرض. بلاده يونيو وتزويده بـ يتم.","marks":[],"data":{}}],"data":{}}]}}},{"sys":{"space":{"sys":{"type":"Link","linkType":"Space","id":"hdgltcjj3ktx"}},"type":"Entry","id":"3yPQeAAH2eNVoWqpetbC6b","contentType":{"sys":{"type":"Link","linkType":"ContentType","id":"image"}},"revision":1,"createdAt":"2019-05-03T10:40:26.610Z","updatedAt":"2019-05-03T10:43:28.768Z","environment":{"sys":{"id":"master","type":"Link","linkType":"Environment"}},"locale":"ar-BH"},"fields":{"image":{"sys":{"space":{"sys":{"type":"Link","linkType":"Space","id":"hdgltcjj3ktx"}},"type":"Asset","id":"3uS9Zm0f570ijZipDqnZ28","revision":1,"createdAt":"2019-05-03T10:41:18.468Z","updatedAt":"2019-05-03T10:41:59.635Z","environment":{"sys":{"id":"master","type":"Link","linkType":"Environment"}},"locale":"ar-BH"},"fields":{"title":"Cat","description":"A Cat","file":{"url":"//images.ctfassets.net/hdgltcjj3ktx/3uS9Zm0f570ijZipDqnZ28/57c08a8c9d49b68b670d10dc7efbe29d/cat.jpg","details":{"size":29786,"image":{"width":500,"height":375}},"fileName":"cat.jpg","contentType":"image/jpeg"}}}}}]}}}